vtransformer/__init__.py
vtransformer/layers.py
vtransformer/model.py
vanilla_transformer_jax-0.0.4.dist-info/LICENSE
vanilla_transformer_jax-0.0.4.dist-info/METADATA
vanilla_transformer_jax-0.0.4.dist-info/WHEEL
vanilla_transformer_jax-0.0.4.dist-info/top_level.txt
vanilla_transformer_jax-0.0.4.dist-info/RECORD
