Metadata-Version: 2.1
Name: vanilla-transformer-jax
Version: 0.0.4
Summary: JAX/Flax implimentation of 'Attention is All You Need' by Vaswani et al.
Home-page: https://github.com/Bhavnicksm/vanilla-transformer-jax
Author: bhavnicksm
Author-email: bhavnicksm@gmail.com
License: UNKNOWN
Project-URL: Bug Tracker, https://github.com/Bhavnicksm/vanilla-transformer-jax/issues
Keywords: transformer,JAX,Flax,Deep-Learning
Platform: UNKNOWN
Classifier: Programming Language :: Python :: 3
Classifier: License :: OSI Approved :: MIT License
Classifier: Operating System :: OS Independent
Requires-Python: >=3.6
License-File: LICENSE
Requires-Dist: jax (>=0.0.0)
Requires-Dist: flax (>=0.0.0)
Requires-Dist: numpy (>=0.0.0)
